tex2ipy/__init__.py
tex2ipy/cli.py
tex2ipy/tex2cells.py
tex2ipy/tests/__init__.py
tex2ipy/tests/test_tex2cells.py
tex2ipy/tests/test_tex2ipy.py
tex2ipy-0.3.dist-info/DESCRIPTION.rst
tex2ipy-0.3.dist-info/METADATA
tex2ipy-0.3.dist-info/RECORD
tex2ipy-0.3.dist-info/WHEEL
tex2ipy-0.3.dist-info/entry_points.txt
tex2ipy-0.3.dist-info/metadata.json
tex2ipy-0.3.dist-info/top_level.txt
